unicms_template_italia/__init__.py
unicms_template_italia/apps.py
unicms_template_italia/settings.py
unicms_template_italia/locale/it/LC_MESSAGES/django.mo
unicms_template_italia/locale/it/LC_MESSAGES/django.po
unicms_template_italia/static/css/vendor/owl.carousel.min.css
unicms_template_italia/static/js/axios.1.9.0.js
unicms_template_italia/static/js/axios.min.js.map
unicms_template_italia/static/js/deferred_iframe_src.js
unicms_template_italia/static/js/external_sources_consent.js
unicms_template_italia/static/js/external_sources_consent.min.js
unicms_template_italia/static/js/jquery.3.7.1.min.js
unicms_template_italia/static/js/passive_listeners.js
unicms_template_italia/static/js/tldts.7.0.17.min.js
unicms_template_italia/static/js/vue.2.7.16.js
unicms_template_italia/static/js/vue.options.js
unicms_template_italia/static/js/vendor/owl.carousel.min.js
unicms_template_italia/templates/bases/unicms_italia.html
unicms_template_italia/templates/blocks/italia_carousel_hero_slider.html
unicms_template_italia/templates/blocks/italia_cookie_consent.html
unicms_template_italia/templates/blocks/italia_heading.html
unicms_template_italia/templates/blocks/italia_link.html
unicms_template_italia/templates/blocks/italia_link_iframe.html
unicms_template_italia/templates/blocks/italia_media_collection_image_grid.html
unicms_template_italia/templates/blocks/italia_media_collection_image_slider.html
unicms_template_italia/templates/blocks/italia_media_collection_image_slider_full.html
unicms_template_italia/templates/blocks/italia_media_collection_list.html
unicms_template_italia/templates/blocks/italia_media_image.html
unicms_template_italia/templates/blocks/italia_menu_main.html
unicms_template_italia/templates/blocks/italia_menu_side.html
unicms_template_italia/templates/blocks/italia_pub_alert.html
unicms_template_italia/templates/blocks/italia_pub_collapse.html
unicms_template_italia/templates/blocks/italia_pub_collapse_logo_image.html
unicms_template_italia-1.4.12.dist-info/licenses/AUTHORS
unicms_template_italia-1.4.12.dist-info/licenses/LICENSE
unicms_template_italia-1.4.12.dist-info/METADATA
unicms_template_italia-1.4.12.dist-info/WHEEL
unicms_template_italia-1.4.12.dist-info/top_level.txt
unicms_template_italia-1.4.12.dist-info/RECORD
